netspeedmonitor/__init__.py
netspeedmonitor/cli.py
netspeedmonitor/gui.py
netspeedmonitor/lib.py
netspeedmonitor/ui.py
netspeedmonitor-0.1.1.dist-info/METADATA
netspeedmonitor-0.1.1.dist-info/WHEEL
netspeedmonitor-0.1.1.dist-info/entry_points.txt
netspeedmonitor-0.1.1.dist-info/top_level.txt
netspeedmonitor-0.1.1.dist-info/RECORD
